snps/__init__.py
snps/_version.py
snps/constants.py
snps/ensembl.py
snps/resources.py
snps/snps.py
snps/utils.py
snps/io/__init__.py
snps/io/reader.py
snps/io/writer.py
snps-2.11.0.dist-info/licenses/LICENSE.txt
snps-2.11.0.dist-info/licenses/LICENSES-3RD-PARTY.txt
snps-2.11.0.dist-info/METADATA
snps-2.11.0.dist-info/WHEEL
snps-2.11.0.dist-info/top_level.txt
snps-2.11.0.dist-info/RECORD
