Metadata-Version: 2.4
Name: snps
Version: 2.11.0
Summary: tools for reading, writing, merging, and remapping SNPs
Home-page: https://github.com/apriha/snps
Author: Andrew Riha
Author-email: apriha@gmail.com
License: BSD 3-Clause License
Project-URL: Documentation, https://snps.readthedocs.io/
Project-URL: Changelog, https://github.com/apriha/snps/releases
Project-URL: Issue Tracker, https://github.com/apriha/snps/issues
Keywords: snps dna chromosomes bioinformatics vcf
Platform: any
Classifier: Development Status :: 5 - Production/Stable
Classifier: Intended Audience :: Developers
Classifier: Intended Audience :: End Users/Desktop
Classifier: Intended Audience :: Healthcare Industry
Classifier: Intended Audience :: Science/Research
Classifier: License :: OSI Approved :: BSD License
Classifier: Natural Language :: English
Classifier: Operating System :: OS Independent
Classifier: Programming Language :: Python :: 3.8
Classifier: Programming Language :: Python :: 3.9
Classifier: Programming Language :: Python :: 3.10
Classifier: Programming Language :: Python :: 3.11
Classifier: Programming Language :: Python :: 3.12
Classifier: Topic :: Scientific/Engineering
Classifier: Topic :: Scientific/Engineering :: Bio-Informatics
Classifier: Topic :: Scientific/Engineering :: Information Analysis
Classifier: Topic :: Utilities
Requires-Python: >=3.8
License-File: LICENSE.txt
License-File: LICENSES-3RD-PARTY.txt
Requires-Dist: numpy
Requires-Dist: pandas
Requires-Dist: atomicwrites
Provides-Extra: ezancestry
Requires-Dist: ezancestry; extra == "ezancestry"
Dynamic: author
Dynamic: author-email
Dynamic: classifier
Dynamic: description
Dynamic: home-page
Dynamic: keywords
Dynamic: license
Dynamic: license-file
Dynamic: platform
Dynamic: project-url
Dynamic: provides-extra
Dynamic: requires-dist
Dynamic: requires-python
Dynamic: summary
